{
  "city_name": "tustin-california",
  "city_rank": 420,
  "city_population": 78327,
  "parameters": {
    "keyword": "capoeira",
    "location": [
      33.7458511,
      -117.826166
    ],
    "rankby": "distance"
  },
  "people_per_result": 6527,
  "possible_duplicates": {},
  "placesResult": {
    "html_attributions": [],
    "results": [
      {
        "geometry": {
          "location": {
            "lat": 33.7405944,
            "lng": -117.8193412
          },
          "viewport": {
            "northeast": {
              "lat": 33.74199368029149,
              "lng": -117.8180678697085
            },
            "southwest": {
              "lat": 33.73929571970849,
              "lng": -117.8207658302915
            }
          }
        },
        "icon": "https://maps.gstatic.com/mapfiles/place_api/icons/school-71.png",
        "id": "2ceac26d764182f29cc1029848c5b3ca10170271",
        "name": "World Hwa Rang Do Association",
        "place_id": "ChIJbc0I_ufb3IARtCk1-K5fbYc",
        "rating": 5,
        "reference": "CmRSAAAAUHFzlJkCrTplbsH-TAn4mpBov0sv9vGgAK3fzkkRoppDZGMImMEaj7JwPG12NEzIdtv6O8posRkvwk1aHRkTuLUy1IUIaoB6qPfT9SW4_49CmaOTsot3iEiuMkUZ-QWzEhD2OUDHddI23A2TzvXX2OQLGhTrER3JbAtEGAJkMBvh5EKoJ_zcOw",
        "scope": "GOOGLE",
        "types": [
          "health",
          "point_of_interest",
          "establishment"
        ],
        "vicinity": "13762 Newport Avenue, Tustin"
      },
      {
        "geometry": {
          "location": {
            "lat": 33.739077,
            "lng": -117.820502
          },
          "viewport": {
            "northeast": {
              "lat": 33.7405498802915,
              "lng": -117.8193315697085
            },
            "southwest": {
              "lat": 33.7378519197085,
              "lng": -117.8220295302915
            }
          }
        },
        "icon": "https://maps.gstatic.com/mapfiles/place_api/icons/school-71.png",
        "id": "cf03ec36dd43cde50e56d83fd5f1e644b4688aa0",
        "name": "Z-Ultimate Self Defense Studios",
        "opening_hours": {
          "open_now": true,
          "weekday_text": []
        },
        "photos": [
          {
            "height": 3456,
            "html_attributions": [
              "<a href=\"https://maps.google.com/maps/contrib/113263927117310653603/photos\">Z-Ultimate Self Defense Studios</a>"
            ],
            "photo_reference": "CmRaAAAA0Dahn6LsVhaVO3CP1Ml_Iy1dKYE3ZtarDiOHQxYfwtSLZ52-7gOTZFbBE3dq-LK09k3kpvlFflX24dL6I-2IjfNbQQjLeV27DI_p7vSFZzsxWcnoCILmysweVswKFxvtEhAuMWc_Tdb_5qgFBu1aW-wsGhQAT4GjXLtRd-oWikG0gP2m-dmkpg",
            "width": 4608
          }
        ],
        "place_id": "ChIJc9MGB-jb3IARi3fbJ2b5l24",
        "rating": 5,
        "reference": "CmRRAAAAhe-Q8UZLkm5VAPqvrw1QzItY9LHHHey1MeAcsh7kjqnznlhPIh3Ps5b5DDPXpnJxYnyAlPjm1oPFuSG1sCdzsCf_5M53Tah1GSFsak6P3y8_ODpah9cKp-x6u1yX6yjWEhBDnXzruC4mWeIPi2rUlv68GhQ9fkvCOAAfaL7CvAZ5MLhmL9cf_g",
        "scope": "GOOGLE",
        "types": [
          "health",
          "point_of_interest",
          "establishment"
        ],
        "vicinity": "13882 Newport Avenue B, Tustin"
      },
      {
        "geometry": {
          "location": {
            "lat": 33.7207316,
            "lng": -117.8269251
          },
          "viewport": {
            "northeast": {
              "lat": 33.7222398802915,
              "lng": -117.8254635697085
            },
            "southwest": {
              "lat": 33.7195419197085,
              "lng": -117.8281615302915
            }
          }
        },
        "icon": "https://maps.gstatic.com/mapfiles/place_api/icons/school-71.png",
        "id": "b30eb8a74f80856920b6ebe38b007bd902d86c81",
        "name": "Carlson Gracie Irvine",
        "opening_hours": {
          "open_now": false,
          "weekday_text": []
        },
        "photos": [
          {
            "height": 640,
            "html_attributions": [
              "<a href=\"https://maps.google.com/maps/contrib/108757303864886355494/photos\">Carlson Gracie Irvine</a>"
            ],
            "photo_reference": "CmRaAAAA35vr4opVEvzuNnYL1tdVNK3vFuilZJEVuZrrXENvy1gzA4ZWxx81MeMT2ZyAOY_6Dv29UA8NXxnko9tX-bC18JCzbtW53jzyWigQ-wVa5DIkD4cyFmBnS8nMxpMI2fk5EhBbGxqQTNJk4zO_WBH1OU80GhRNz1IS1b-a7h13kJs7dMYTaKLxLA",
            "width": 960
          }
        ],
        "place_id": "ChIJsQ3WGP_b3IARyvxPyiByJeA",
        "rating": 5,
        "reference": "CmRSAAAAJhPOYD5PVspxMQOhNJ4u5Iyq7rCNj5IhSGXYf4CJqc7Sv4FlW61ePafecrVYxLXZV_eKCJzOMWvLnQ6VqqyYNCrQVE57jiebOkAgqYbyS4TULGH7ZT9aLqQaU1V6ok3YEhC932dIa0RqUIJI8dOf_MeJGhQbI7vcXoqBHWBFov3rE5MYMs-zng",
        "scope": "GOOGLE",
        "types": [
          "health",
          "point_of_interest",
          "establishment"
        ],
        "vicinity": "1542 Edinger Avenue, Tustin"
      },
      {
        "geometry": {
          "location": {
            "lat": 33.770085,
            "lng": -117.835005
          },
          "viewport": {
            "northeast": {
              "lat": 33.7714351802915,
              "lng": -117.8340375197085
            },
            "southwest": {
              "lat": 33.76873721970851,
              "lng": -117.8367354802915
            }
          }
        },
        "icon": "https://maps.gstatic.com/mapfiles/place_api/icons/school-71.png",
        "id": "00cd63da622a4ef6b3be22eee029700bc82e028a",
        "name": "Carrillo Muay Thai Boxing & Striking for MMA",
        "opening_hours": {
          "open_now": true,
          "weekday_text": []
        },
        "photos": [
          {
            "height": 540,
            "html_attributions": [
              "<a href=\"https://maps.google.com/maps/contrib/116405885557020910672/photos\">Carrillo Muay Thai Boxing &amp; Striking for MMA</a>"
            ],
            "photo_reference": "CmRaAAAA6fSmkfLuXIqLdjaYlNLOV9ec8BzIY1MPXWqMZ9efl59QnhWnvD8-MbSpzatFwQP7ajNfnE7eTzIjZI-4luCzIxkn4T2C7gigkeWOjZvzez1qhEpXykTONwFaGohoR7wYEhCKeI5PO6HzZCeR30cPBVwiGhSoTa8n5xVKjuZ5jTERI86AQV6lrA",
            "width": 960
          }
        ],
        "place_id": "ChIJKbLlakfZ3IARz7qzu4xpJ5E",
        "rating": 4.8,
        "reference": "CmRSAAAAu_dI7I8ScZ8jBUDGSUnNR4gPdpsNZLk_t1ZoUHekNQajFt4zKYe36AZLqXARpbgcICu-StO_Ck0KYT7tSudurrtgIaXl75nnKpVom4-fYuxJIsC1jUm2YIbhBYAKAUsMEhBzt487-HF0dsyLXE5OZjEzGhR1Z6q5gks2rLKlP4pE3kbYZyFTcg",
        "scope": "GOOGLE",
        "types": [
          "health",
          "point_of_interest",
          "establishment"
        ],
        "vicinity": "2431 North Tustin Avenue c, Santa Ana"
      },
      {
        "geometry": {
          "location": {
            "lat": 33.71357,
            "lng": -117.802116
          },
          "viewport": {
            "northeast": {
              "lat": 33.7150010302915,
              "lng": -117.8014219197085
            },
            "southwest": {
              "lat": 33.7123030697085,
              "lng": -117.8041198802915
            }
          }
        },
        "icon": "https://maps.gstatic.com/mapfiles/place_api/icons/school-71.png",
        "id": "365931603324974828dae17aff1c8ac5eee6293c",
        "name": "Tajik Karate",
        "opening_hours": {
          "open_now": false,
          "weekday_text": []
        },
        "photos": [
          {
            "height": 759,
            "html_attributions": [
              "<a href=\"https://maps.google.com/maps/contrib/103376560941796810797/photos\">Tajik Karate</a>"
            ],
            "photo_reference": "CmRaAAAA9LWsn8EmkFJ1sMD71TR-HxlmArrxsivK6jIIJYjHZrk6CDzW0H1OfDPaq4gNSteC7d1QUDosn90sYQxB_acrHEvLxprGb1X8RDLxB63w5_HG__20dCC1R2uZ-DVaDnJwEhCVWxCP5qtYfIrZkZheA8p4GhSZOA6uTPHbf8R_rKn3YbpV_3k0iA",
            "width": 758
          }
        ],
        "place_id": "ChIJTeLcAuLc3IARZAP07Dcs-IY",
        "rating": 5,
        "reference": "CmRSAAAAxK5IrGws5eneVo7f6FsA-5Ua9ziv5fsR2A93bkuQz57lomkWkTVyc1OX6uvTrluT9Z1rjOA3pTGXGt3U2i2R8c1jGlQM701gDaEljfqSJSdTRxBWaaBZW-MidXyCdHaKEhA7tCLBPg1QqAVt8nBB-YaAGhStCCuJEZrTTVKJ0fGADYrsLUucUQ",
        "scope": "GOOGLE",
        "types": [
          "health",
          "point_of_interest",
          "establishment"
        ],
        "vicinity": "14522 Myford Road, Irvine"
      },
      {
        "geometry": {
          "location": {
            "lat": 33.7114543,
            "lng": -117.8510372
          },
          "viewport": {
            "northeast": {
              "lat": 33.7128013802915,
              "lng": -117.8495235197085
            },
            "southwest": {
              "lat": 33.7101034197085,
              "lng": -117.8522214802915
            }
          }
        },
        "icon": "https://maps.gstatic.com/mapfiles/place_api/icons/school-71.png",
        "id": "fa89e8ad9ea059104d77aa56d47bcee8a0910d97",
        "name": "Angelito Boxing",
        "place_id": "ChIJocRC6LTe3IARU99K5TyqINA",
        "reference": "CmRSAAAArIdU4AUoDoLNbe7Xm2J51tGBjpSuBYaRba-iS54Ee_JH6t_FqDzN-u1iV2kcf01V-vtLfD-h_wKHEU8jbzjIKccCE38l4OduCpUgI0QIv3F_C0JZnidoEoKtfoTenD6DEhDn58rLzpAQP5-bwzLO_vFNGhSzIied6QFXkqTQ4yuqM8EPPO5IpA",
        "scope": "GOOGLE",
        "types": [
          "gym",
          "health",
          "point_of_interest",
          "establishment"
        ],
        "vicinity": "2654 South Grand Avenue, Santa Ana"
      },
      {
        "geometry": {
          "location": {
            "lat": 33.8025461,
            "lng": -117.8364982
          },
          "viewport": {
            "northeast": {
              "lat": 33.8037756802915,
              "lng": -117.8351498697085
            },
            "southwest": {
              "lat": 33.8010777197085,
              "lng": -117.8378478302915
            }
          }
        },
        "icon": "https://maps.gstatic.com/mapfiles/place_api/icons/school-71.png",
        "id": "1516fc48ba6a626234d7bdc9a7462179f2dfc06a",
        "name": "UFC Gym Orange",
        "opening_hours": {
          "open_now": true,
          "weekday_text": []
        },
        "photos": [
          {
            "height": 700,
            "html_attributions": [
              "<a href=\"https://maps.google.com/maps/contrib/113147290502488809364/photos\">UFC Gym Orange</a>"
            ],
            "photo_reference": "CmRaAAAA0b5MBaWuRVrPAy9SiZRMKei_oONLZby12ak63_FhAcaVyKe8vmmthA1Iqb88N2RATqwvsHestOW3sgSVFBuwp4irVPrdKMyTLXuTHfDzGyUcXFlIavx4YWIGZV3ZyNPDEhC0PurTxwLP5ahsJ-URcRdKGhQmfVyLoLwHJk5ZPjQp_z_k_qeceg",
            "width": 702
          }
        ],
        "place_id": "ChIJm-DpIVTX3IARyft60wtqHXo",
        "rating": 5,
        "reference": "CmRRAAAATW4o5Xr_T_T_8GgJO5c0nTOtDjm0q4wTqtBhVuxNLUG8Fwt-BO3uHgavhwa7Erl30KasiCaUmJCzL3G94Yarx0Pf65z0-1XhGiyDt3kBuSlSuh9tKNF6KDJOlUEi-tv_EhBs7SWhy0tKWxbaKE0ZuinyGhTINwsKQiTSxr0zN-tt9OFvzJeWJw",
        "scope": "GOOGLE",
        "types": [
          "gym",
          "health",
          "point_of_interest",
          "establishment"
        ],
        "vicinity": "1605 East Collins Avenue, Orange"
      },
      {
        "geometry": {
          "location": {
            "lat": 33.7113392,
            "lng": -117.7591934
          },
          "viewport": {
            "northeast": {
              "lat": 33.7131944302915,
              "lng": -117.7573379197085
            },
            "southwest": {
              "lat": 33.7104964697085,
              "lng": -117.7600358802915
            }
          }
        },
        "icon": "https://maps.gstatic.com/mapfiles/place_api/icons/school-71.png",
        "id": "a7a01a0c5310e30490776b285d77b28d2b8617f8",
        "name": "United Studios of Self Defense",
        "photos": [
          {
            "height": 2367,
            "html_attributions": [
              "<a href=\"https://maps.google.com/maps/contrib/113535072359664397670/photos\">EM Abalos</a>"
            ],
            "photo_reference": "CmRaAAAAH52lHacABaPGsLJp1ZCgMo_0M_YGYtaePHBvhl6x07BvV8R4w6YF10yOHRAyVw_jDvj1NU8y2WkCbRXr2g2tsOsFtcmePq5yVv-x_cYbQuu87tfM08L3OgcFTp6odn2CEhDi8otJQ5IUHP8WE30RdddcGhSopEdl1Ox50SmraB-smCH-rTHw_A",
            "width": 2496
          }
        ],
        "place_id": "ChIJj2pvtsHc3IARUQmrvXv7Ghg",
        "rating": 5,
        "reference": "CmRRAAAAvBJVHT1Wt58GmKdR188UK-wOiNTaEeelxti_ZwXsHg-VULbernFRELfMQmXJ5m6t_uevTpmA9RgJNXVoIbblL5NniaStzJWUwPf3lQBQoWe9czrjI2mPHAKtAd7ThSclEhA3a9du4DHaLF-2fuMNFj35GhSztvyd39PUXaBnCefJtsJKc4t-EA",
        "scope": "GOOGLE",
        "types": [
          "health",
          "point_of_interest",
          "establishment"
        ],
        "vicinity": "4960 Irvine Boulevard # 101, Irvine"
      },
      {
        "geometry": {
          "location": {
            "lat": 33.6809383,
            "lng": -117.7790654
          },
          "viewport": {
            "northeast": {
              "lat": 33.6820243802915,
              "lng": -117.7771589697085
            },
            "southwest": {
              "lat": 33.6793264197085,
              "lng": -117.7798569302915
            }
          }
        },
        "icon": "https://maps.gstatic.com/mapfiles/place_api/icons/school-71.png",
        "id": "b2c3a305ed85139100dcf529e83debdbf36b871d",
        "name": "Capoeira Batuque Irvine",
        "opening_hours": {
          "open_now": true,
          "weekday_text": []
        },
        "photos": [
          {
            "height": 2448,
            "html_attributions": [
              "<a href=\"https://maps.google.com/maps/contrib/114495111919772689791/photos\">Capoeira Batuque Irvine</a>"
            ],
            "photo_reference": "CmRZAAAA2yCz8W9nnjqovljSF0nvi4o_cDOva4SH7DVtCGUE2fPNUhs5ZRyVmF8BNlC4H7_sIEdsz7_0zTEBw0QEOdrScoYW1koGjIPHkn3dFuDMiVAbtQz9okCgPlx2YwdNWWR0EhCpgJoiQmlxHhD_Sy7eeXvPGhSMWCXb4DVJIEm5zpB4-3r08doe1g",
            "width": 3264
          }
        ],
        "place_id": "ChIJR_8UfAbd3IARhHJNSCqoEx8",
        "rating": 5,
        "reference": "CmRRAAAAKDc_TG5kKT-QDGtez4cLe-aoLcjkO6-LNjsf7wbVqeHBnSR1bP_1wtSLVtvG80jQCE3jVIaMYsXTxcIHnbCl2LNto1dZTV5jEsW9rK_wi_7z4gyJanJ5lF3AD2E9EEyEEhCSxOqxPonG-dZENaPlyCNNGhTl7v6HcFZ-R9FjMAAy4fbHmG321Q",
        "scope": "GOOGLE",
        "types": [
          "health",
          "point_of_interest",
          "establishment"
        ],
        "vicinity": "15435 Jeffrey Road #100, Irvine"
      },
      {
        "geometry": {
          "location": {
            "lat": 33.6550863,
            "lng": -117.9194759
          },
          "viewport": {
            "northeast": {
              "lat": 33.6564368302915,
              "lng": -117.9179431197085
            },
            "southwest": {
              "lat": 33.6537388697085,
              "lng": -117.9206410802915
            }
          }
        },
        "icon": "https://maps.gstatic.com/mapfiles/place_api/icons/school-71.png",
        "id": "c06ddc2b38ef3baf0a885a954b50ca2eddb81218",
        "name": "Capoeira Brasil Orange County",
        "place_id": "ChIJNYBpUX_f3IARfLrZ75yCbJE",
        "reference": "CmRSAAAAMs4uoHlt9GnOASUtW4ZjibRKUOTCTn-UmwnkdsLZAqk2eQn6UhL8TuGckg6QqgXQrySfUnKuRnyP50413Ia_oKji4jbJOPeB0gxrartEsFwWMiqYGk3DF9QRNYIOTNxwEhBOwq598ACSPMs6oUcwltbrGhQmRGUKvRar1C8p11tOG58DaNvjFA",
        "scope": "GOOGLE",
        "types": [
          "point_of_interest",
          "establishment"
        ],
        "vicinity": "2221 Harbor Boulevard, Costa Mesa"
      },
      {
        "geometry": {
          "location": {
            "lat": 33.7746675,
            "lng": -118.1649725
          },
          "viewport": {
            "northeast": {
              "lat": 33.7763544302915,
              "lng": -118.1636221197085
            },
            "southwest": {
              "lat": 33.77365646970851,
              "lng": -118.1663200802915
            }
          }
        },
        "icon": "https://maps.gstatic.com/mapfiles/place_api/icons/school-71.png",
        "id": "73621c705c38aacf7a9ffd4003b44937dd36ea47",
        "name": "BodySport Capoeira - Mestre Roque",
        "opening_hours": {
          "open_now": false,
          "weekday_text": []
        },
        "photos": [
          {
            "height": 1645,
            "html_attributions": [
              "<a href=\"https://maps.google.com/maps/contrib/117079678175180141859/photos\">BodySport Capoeira - Mestre Roque</a>"
            ],
            "photo_reference": "CmRaAAAAzGqISrjf2utWCXT1O16tOHqZkHjgiDGd6IfPOLAMQWn6lidD-BjMAPkwWBJ3Z1poOVTZtr4NxSLUAUKYYD1BRCAmU74qwhr3xINvzkVKDIHD81uRfk45lrXfOYIhjreWEhCEEk72DlnQvvVCtkfeQt2LGhSRiYgQnyE4R2kvviwd99qslYm8fA",
            "width": 2048
          }
        ],
        "place_id": "ChIJ_-829gsx3YAR20XLlgO3fX8",
        "rating": 4.2,
        "reference": "CmRRAAAApJ4EZ0d5gQ-Gb5kx_37psfql_NRL8rIjMnXnWyALEw5G9xH8LBPI1-HnvTkA7HUgWE93CJB1k9LqzQ7-SqCPtZu6gqqJwMZON7UKQMzFvWgDSR-k6aGxNwtp4KbtwWsqEhB11CbMUse6wPx2mLkFvswCGhTAK5cdGPsJbkXHLDfMfKx-cqwYZg",
        "scope": "GOOGLE",
        "types": [
          "health",
          "point_of_interest",
          "establishment"
        ],
        "vicinity": "2236 East 7th Street, Long Beach"
      },
      {
        "geometry": {
          "location": {
            "lat": 33.805968,
            "lng": -118.319601
          },
          "viewport": {
            "northeast": {
              "lat": 33.8072800302915,
              "lng": -118.3184028197085
            },
            "southwest": {
              "lat": 33.8045820697085,
              "lng": -118.3211007802915
            }
          }
        },
        "icon": "https://maps.gstatic.com/mapfiles/place_api/icons/school-71.png",
        "id": "1a84c7f20f89e9407814c1b7910b65509ad69769",
        "name": "Arteluta Capoeira Academy",
        "opening_hours": {
          "open_now": false,
          "weekday_text": []
        },
        "photos": [
          {
            "height": 612,
            "html_attributions": [
              "<a href=\"https://maps.google.com/maps/contrib/101934458797649746712/photos\">Arteluta Capoeira Academy</a>"
            ],
            "photo_reference": "CmRaAAAANHp_JBgOi8GArJllnUFaOp_nBURTZryTqLb4FhPaI7Paa_emL5iIOCRUzlpggboNS2bh85ZBsWxGh8ygk-pCQf4n2TnuaWIxD-n__pDNq7I9pe1138yLqaci-5An6LCJEhCt5Z-UcFadMv6qQIKkwGxVGhTddpffWunonw-UBf2RbAPVfLyBSg",
            "width": 816
          }
        ],
        "place_id": "ChIJKwflp4tK3YAROears9HvyF4",
        "rating": 5,
        "reference": "CmRRAAAAnLNKQlsU-hOn7gesHqFWhSs3wIF3bsb0bbKMRbX6ID3zY61Oi_fD_xGHSmJP8_miqqQwXBTLZvmEQKLPGMD3biYfaP9uWQ_rv53kzSnjb9y20saeNgjZZK_Z4hcm05WMEhCYlaeuy9DYeI5Ide7drLWCGhRqScwY8gsJPb8yYIyHA9UEWqix2Q",
        "scope": "GOOGLE",
        "types": [
          "school",
          "health",
          "point_of_interest",
          "establishment"
        ],
        "vicinity": "24100 Narbonne Avenue Suite 107, Lomita"
      }
    ],
    "status": "OK"
  }
}