{
  "city_name": "titusville-florida",
  "city_rank": 833,
  "city_population": 44206,
  "parameters": {
    "keyword": "capoeira",
    "location": [
      28.6122187,
      -80.8075537
    ],
    "rankby": "distance"
  },
  "people_per_result": 44206,
  "possible_duplicates": {},
  "placesResult": {
    "html_attributions": [],
    "results": [
      {
        "geometry": {
          "location": {
            "lat": 28.54785,
            "lng": -81.19394899999999
          },
          "viewport": {
            "northeast": {
              "lat": 28.54921327989272,
              "lng": -81.19276707010728
            },
            "southwest": {
              "lat": 28.54651362010728,
              "lng": -81.19546672989271
            }
          }
        },
        "icon": "https://maps.gstatic.com/mapfiles/place_api/icons/school-71.png",
        "id": "851a1ee8c362df27e77f3c52124d8ee1ecbdf1c6",
        "name": "Capoeira Orlando",
        "opening_hours": {
          "open_now": true
        },
        "photos": [
          {
            "height": 540,
            "html_attributions": [
              "<a href=\"https://maps.google.com/maps/contrib/106337485680687607386/photos\">Capoeira Orlando</a>"
            ],
            "photo_reference": "CmRaAAAAVzjGsitDpRFI47WMj0LhOM4uxqTARt8slPOYy3oUswu2n3_uvfkBLxUnSfsM7948mBCK5Pi7dhKm-VimwLZSUF37ayA2sLmsgHMwrMc4FGUooWzLrx0aJYvZXexIgcw7EhBe5W7nqqDuOX5HhtoisBebGhQ47I0qbhnP9I7_mxdcP3PYoLL_nQ",
            "width": 960
          }
        ],
        "place_id": "ChIJw-fIa5pl54gRrcYaXFIEMMs",
        "plus_code": {
          "compound_code": "GRX4+4C Union Park, Florida",
          "global_code": "76WWGRX4+4C"
        },
        "rating": 5,
        "reference": "ChIJw-fIa5pl54gRrcYaXFIEMMs",
        "scope": "GOOGLE",
        "types": [
          "health",
          "point_of_interest",
          "establishment"
        ],
        "vicinity": "829 Woodbury Road #102, Orlando"
      }
    ],
    "status": "OK"
  }
}