{
  "city_name": "semarang-id",
  "city_rank": 193,
  "city_population": 1288221,
  "parameters": {
    "keyword": "capoeira",
    "location": [
      "-6.9932",
      "110.4203"
    ],
    "rankby": "distance"
  },
  "people_per_result": 1288221,
  "possible_duplicates": {},
  "placesResult": {
    "html_attributions": [],
    "results": [
      {
        "geometry": {
          "location": {
            "lat": -7.023722399999999,
            "lng": 110.4027134
          },
          "viewport": {
            "northeast": {
              "lat": -7.022373419708496,
              "lng": 110.4040623802915
            },
            "southwest": {
              "lat": -7.025071380291501,
              "lng": 110.4013644197085
            }
          }
        },
        "icon": "https://maps.gstatic.com/mapfiles/place_api/icons/generic_business-71.png",
        "id": "b95386bc99257d329d909f59c7a37c8bfb7c4832",
        "name": "Capoeira Cordão De Ouro Unika Soegijapranata",
        "opening_hours": {
          "open_now": false,
          "weekday_text": []
        },
        "photos": [
          {
            "height": 864,
            "html_attributions": [
              "<a href=\"https://maps.google.com/maps/contrib/117362148752026353471/photos\">Mario Eduardo</a>"
            ],
            "photo_reference": "CmRaAAAAM7HSey8kpCdYeWqApFLV4KehKbE7bymC8C4tKmNIEpQLMd5eYFq7tssDKFeL3G1OlB-1vlutuPe0_6b4Hl9U08doXaeSsjRsFs2XSzYvM74XJNuYMGV3b8lOte86KdXZEhDKXkctuu6LBIRtAu_DqcHlGhTjyL6DwGFGrmBKu2YOEkCtg9sa3Q",
            "width": 1152
          }
        ],
        "place_id": "ChIJi_V8nJiLcC4R7gBWDOv2DfY",
        "rating": 5,
        "reference": "CmRSAAAAIXQsSMldzvddCpcYJGB8Lt7rGm0MQ_v616scttTbO_IfXL-OD-TSVuJ_VhAdxz11W5OW1nwZqPAhaZClGFZ3NvVBg6pbS0eMMgirUONeu1XQ8thRh3sklvky0J31mHAKEhBmQ5W1EW6LUKneJTiFdoimGhS7ETm1AZFeGFiB8hFTc1nbmtmGMA",
        "scope": "GOOGLE",
        "types": [
          "gym",
          "health",
          "point_of_interest",
          "establishment"
        ],
        "vicinity": "Sport Center Unika, Bendan Duwur, Gajahmungkur, Tinjomoyo"
      }
    ],
    "status": "OK"
  }
}