{
  "city_name": "st-charles-missouri",
  "city_rank": 507,
  "city_population": 67569,
  "parameters": {
    "keyword": "capoeira",
    "location": [
      38.7881062,
      -90.4974359
    ],
    "rankby": "distance"
  },
  "people_per_result": 16892,
  "possible_duplicates": {},
  "placesResult": {
    "html_attributions": [],
    "results": [
      {
        "geometry": {
          "location": {
            "lat": 38.7499393,
            "lng": -90.3002868
          },
          "viewport": {
            "northeast": {
              "lat": 38.75134182989272,
              "lng": -90.29869162010728
            },
            "southwest": {
              "lat": 38.74864217010727,
              "lng": -90.30139127989271
            }
          }
        },
        "icon": "https://maps.gstatic.com/mapfiles/place_api/icons/school-71.png",
        "id": "4b5d436b852b98e2c439f4d85b4d25d08f214782",
        "name": "Capoeira Angola Study Group St. Louis",
        "opening_hours": {
          "open_now": false,
          "weekday_text": []
        },
        "photos": [
          {
            "height": 1153,
            "html_attributions": [
              "<a href=\"https://maps.google.com/maps/contrib/102123304886412909997/photos\">Capoeira Angola St. Louis</a>"
            ],
            "photo_reference": "CmRaAAAAIvmzVAGODNC7OvvoLH1-4GZH66-8efyWIMUSVvzr996C6kAP4O3HWwMhCcoQ2A1lbP2aYs0JiNMnrhrChrF3IUHY7KNSIYmCtUj_saGlUAvyXDq48PKRUdwkPkUqe26_EhDYRmnbgSu21d0UXK7yz3hjGhSZe8xoL2UwIwtliFI4TBhj67OqPQ",
            "width": 1154
          }
        ],
        "place_id": "ChIJO2Z9pqnK2IcRTeWNWuCxiAg",
        "rating": 5,
        "reference": "CmRbAAAAEXKj68PtR3yIar1i8LDHFBM8lICuWpDKkxVr_xASP7-hQaVD471GQHptgZU_hciimD5g_0vO3Ew0UVviW0k3t8y0Oahf9t-galn4Ai7Ti-mjsK9It6wDiIFOJdlgvL3XEhAfqVDIEqokVxmhL_k1Fn1EGhRWkPUvj-DYwVI1uHE631U7wrr-ug",
        "scope": "GOOGLE",
        "types": [
          "health",
          "point_of_interest",
          "establishment"
        ],
        "vicinity": "303 N Elizabeth Ave, Ferguson"
      },
      {
        "geometry": {
          "location": {
            "lat": 38.6362042,
            "lng": -90.344196
          },
          "viewport": {
            "northeast": {
              "lat": 38.63755402989271,
              "lng": -90.34284617010726
            },
            "southwest": {
              "lat": 38.63485437010727,
              "lng": -90.34554582989271
            }
          }
        },
        "icon": "https://maps.gstatic.com/mapfiles/place_api/icons/school-71.png",
        "id": "c8d76373a4180b97275441c2216b01700b13d008",
        "name": "Capoeira Luanda St. Louis",
        "opening_hours": {
          "open_now": false,
          "weekday_text": []
        },
        "photos": [
          {
            "height": 314,
            "html_attributions": [
              "<a href=\"https://maps.google.com/maps/contrib/113146637515059221929/photos\">Capoeira Luanda St. Louis .</a>"
            ],
            "photo_reference": "CmRaAAAAMjccWcY7mhgrUzYx44fNUgCPbHH3ECUGtU9XaoFW1XudSeir59EkjFUDimRKeRubvqeUfJmMtauO5VgYXSx-S1eDrRIcEUQoZRrDUHbzQyX0B2CnkgxwAeQF3Uy-99jIEhCEOJgoZugPloI_9i3BEx9fGhTrQOtLL6tUjcAgTV4fR0m-CDsZ6g",
            "width": 479
          }
        ],
        "place_id": "ChIJA6C8boa22IcRSkj5cK81rgo",
        "rating": 5,
        "reference": "CmRbAAAAFAI-ts_i2fzzqYBp6OnEHrK6nGnupdGREHw5JRrBkEebdG77aJmdB-fIU_d-gfTs6rQJ7s-K_btz0ufbZHBfs_mIaAp68L5Hw39_I1-Asmog_hP59b5kqeRk1GtC0axtEhBBQSU6mODsSCRe3vvhsqOkGhTdTNAeGj-8v40OWRZRho3Up09Xuw",
        "scope": "GOOGLE",
        "types": [
          "health",
          "point_of_interest",
          "establishment"
        ],
        "vicinity": "1034 S Brentwood Blvd #1600, St. Louis"
      },
      {
        "geometry": {
          "location": {
            "lat": 38.6491835,
            "lng": -90.2947961
          },
          "viewport": {
            "northeast": {
              "lat": 38.65063442989272,
              "lng": -90.29343062010729
            },
            "southwest": {
              "lat": 38.64793477010728,
              "lng": -90.29613027989272
            }
          }
        },
        "icon": "https://maps.gstatic.com/mapfiles/place_api/icons/generic_business-71.png",
        "id": "d4e36b7bd540fd589fe100af8d0e8f7966bde9d2",
        "name": "Axé Capoeira St. Louis",
        "opening_hours": {
          "open_now": false,
          "weekday_text": []
        },
        "photos": [
          {
            "height": 4000,
            "html_attributions": [
              "<a href=\"https://maps.google.com/maps/contrib/101391877661171791604/photos\">Grupo Axé Capoeira St. Louis</a>"
            ],
            "photo_reference": "CmRaAAAAlQkFW-ga5r_zS5Bwsi1-0BY1hF8BZ-zRb_Xu0lFftlCC4lAdLIxLI_6S3IsgJDTjhkIVkFTY8uXzhtj20LePV20kHJ-_I6e-qxkv1cpiZhEF8RJs-jiVz0xw8UmWRXF1EhDjnztl6ydG7REKwzN2RT2wGhR-TeNHuXYeYOROp8grdGHA-EnTnw",
            "width": 6000
          }
        ],
        "place_id": "ChIJqQBLiFO12IcRy6V7O0swv10",
        "rating": 5,
        "reference": "CmRbAAAAjW_8WA4d7sl6fQZh2iujpO0WmbYsHd-htVcEk2oiQ4IskNVFajfS8OIBrSNNFopfbMjmta2KjFbgWXO6SaTwIosErGX7ac6PqdpfXSM4RkE8Eo2uScn00nnI5nbKtSMvEhBK4dwI3ADqDA48LFl8ac92GhST6INa0FDowQC5_ESX9_ZKlIanBQ",
        "scope": "GOOGLE",
        "types": [
          "health",
          "school",
          "point_of_interest",
          "establishment"
        ],
        "vicinity": "6002 Pershing Ave, St. Louis"
      },
      {
        "geometry": {
          "location": {
            "lat": 38.92507,
            "lng": -90.172412
          },
          "viewport": {
            "northeast": {
              "lat": 38.92641982989273,
              "lng": -90.17106217010728
            },
            "southwest": {
              "lat": 38.92372017010728,
              "lng": -90.17376182989273
            }
          }
        },
        "icon": "https://maps.gstatic.com/mapfiles/place_api/icons/school-71.png",
        "id": "408d713d1a0ce9de8795c4a20f9270eb8c9ee7c8",
        "name": "Alton Capoeira",
        "opening_hours": {
          "open_now": false,
          "weekday_text": []
        },
        "photos": [
          {
            "height": 453,
            "html_attributions": [
              "<a href=\"https://maps.google.com/maps/contrib/100759062889294576920/photos\">Alton Capoeira</a>"
            ],
            "photo_reference": "CmRaAAAA9WvjGmasu7cS_GrjRjJpMEip6bBvSSB8m46VQb_K3_NLNU-agaCn25kxEKUw3zilCmabqiOREeLNW8cjANO2BVAtqnLB60HYv44WdbyOOuch0zql6vNWCHcLgJNwDX2bEhD8vZs415IZppw6CxwCanRrGhTvFB_fIqB5dTUto3aaNxyd2Qc45Q",
            "width": 604
          }
        ],
        "place_id": "ChIJ1YNfYURD34cRMxsh6jdOThU",
        "reference": "CmRbAAAA_fpO-HvA8CwMx5Z2R_9qlDsZYrYeoQmm2StnZjKc2CWeQF_Sinn1qy5lWXmQNysauAaQuX1S5A4o2zNX3ob3RNBYUfb1ceAcNfksT5C5lbT837wBYKBkxD-JfcWcsAb9EhCeXr--iEdAT4-A5eldUENRGhQYy7nuLbJ9p6mhIWymsETj35vVjg",
        "scope": "GOOGLE",
        "types": [
          "health",
          "point_of_interest",
          "establishment"
        ],
        "vicinity": "221 Center Dr., Be Well Now, Alton"
      }
    ],
    "status": "OK"
  }
}